{
    "name": "The Maze",
    "description": "A complex network of paths requires masterful tower placement and timing.",
    "mapImage": {
        "url": "/assets/maps/05_the_maze.png"
    },
    "gameMap": {
        "rows": 17,
        "columns": 25,
        "cells": [
            [1, 1, 1, 1, 1, 1, 1, 1, 1, 1, 1, 1, 1, 1, 1, 1, 1, 1, 1, 1, 1, 1, 1, 1, 1],
            [1, 1, 1, 1, 1, 1, 1, 1, 1, 1, 1, 1, 1, 1, 1, 1, 1, 1, 1, 1, 1, 1, 1, 1, 1],
            [1, 1, 1, 1, 1, 1, 1, 1, 1, 1, 1, 1, 1, 1, 1, 1, 1, 1, 1, 1, 1, 1, 1, 1, 1],
            [1, 1, 1, 1, 1, 1, 1, 1, 1, 1, 1, 1, 1, 1, 1, 1, 1, 1, 1, 1, 1, 1, 1, 1, 1],
            [1, 1, 1, 1, 1, 1, 1, 1, 1, 1, 1, 1, 1, 1, 1, 1, 1, 1, 1, 1, 1, 1, 1, 1, 1],
            [1, 1, 1, 1, 1, 1, 1, 1, 1, 1, 1, 1, 1, 1, 1, 1, 1, 1, 1, 1, 1, 1, 1, 1, 1],
            [1, 1, 1, 1, 1, 1, 1, 1, 1, 1, 1, 1, 1, 1, 1, 1, 1, 1, 1, 1, 1, 1, 1, 1, 1],
            [1, 1, 1, 1, 1, 1, 1, 1, 1, 1, 1, 1, 1, 1, 1, 1, 1, 1, 1, 1, 1, 1, 1, 1, 1],
            [1, 1, 1, 1, 1, 1, 1, 1, 1, 1, 1, 1, 1, 1, 1, 1, 1, 1, 1, 1, 1, 1, 1, 1, 1],
            [1, 1, 1, 1, 1, 1, 1, 1, 1, 1, 1, 1, 1, 1, 1, 1, 1, 1, 1, 1, 1, 1, 1, 1, 1],
            [1, 1, 1, 1, 1, 1, 1, 1, 1, 1, 1, 1, 1, 1, 1, 1, 1, 1, 1, 1, 1, 1, 1, 1, 1],
            [1, 1, 1, 1, 1, 1, 1, 1, 1, 1, 1, 1, 1, 1, 1, 1, 1, 1, 1, 1, 1, 1, 1, 1, 1],
            [1, 1, 1, 1, 1, 1, 1, 1, 1, 1, 1, 1, 1, 1, 1, 1, 1, 1, 1, 1, 1, 1, 1, 1, 1],
            [1, 1, 1, 1, 1, 1, 1, 1, 1, 1, 1, 1, 1, 1, 1, 1, 1, 1, 1, 1, 1, 1, 1, 1, 1],
            [1, 1, 1, 1, 1, 1, 1, 1, 1, 1, 1, 1, 1, 1, 1, 1, 1, 1, 1, 1, 1, 1, 1, 1, 1],
            [1, 1, 1, 1, 1, 1, 1, 1, 1, 1, 1, 1, 1, 1, 1, 1, 1, 1, 1, 1, 1, 1, 1, 1, 1],
            [1, 1, 1, 1, 1, 1, 1, 1, 1, 1, 1, 1, 1, 1, 1, 1, 1, 1, 1, 1, 1, 1, 1, 1, 1]
        ],
        "paths": [
            [
                [0, 1],
                [1, 1],
                [2, 1],
                [3, 1],
                [4, 1],
                [5, 1],
                [6, 1],
                [7, 1],
                [8, 1],
                [9, 1],
                [10, 1],
                [11, 1],
                [12, 1],
                [13, 1],
                [14, 1],
                [15, 1],
                [16, 1],
                [17, 1],
                [17, 2],
                [17, 3],
                [17, 4],
                [17, 5],
                [17, 6],
                [17, 7],
                [17, 8],
                [17, 9],
                [17, 10],
                [17, 11],
                [17, 12],
                [17, 13],
                [17, 14],
                [16, 14],
                [15, 14],
                [14, 14],
                [13, 14],
                [12, 14],
                [11, 14],
                [10, 14],
                [9, 14],
                [8, 14],
                [7, 14],
                [6, 14],
                [5, 14],
                [5, 13],
                [5, 12],
                [5, 11],
                [5, 10],
                [5, 9],
                [6, 9],
                [7, 9],
                [8, 9],
                [9, 9],
                [10, 9],
                [10, 10],
                [10, 11],
                [11, 11],
                [12, 11],
                [13, 11],
                [14, 11],
                [14, 10],
                [14, 9],
                [14, 8],
                [14, 7],
                [15, 7],
                [16, 7],
                [17, 7],
                [18, 7],
                [19, 7],
                [20, 7],
                [21, 7],
                [22, 7],
                [22, 8],
                [23, 8],
                [24, 8]
            ],
            [
                [0, 15],
                [1, 15],
                [2, 15],
                [2, 14],
                [2, 13],
                [2, 12],
                [2, 11],
                [2, 10],
                [2, 9],
                [2, 8],
                [2, 7],
                [2, 6],
                [2, 5],
                [2, 4],
                [3, 4],
                [4, 4],
                [5, 4],
                [6, 4],
                [7, 4],
                [8, 4],
                [9, 4],
                [10, 4],
                [11, 4],
                [12, 4],
                [13, 4],
                [14, 4],
                [14, 5],
                [14, 6],
                [14, 7],
                [14, 8],
                [14, 9],
                [14, 10],
                [14, 11],
                [13, 11],
                [12, 11],
                [11, 11],
                [10, 11],
                [10, 10],
                [10, 9],
                [9, 9],
                [8, 9],
                [7, 9],
                [6, 9],
                [5, 9],
                [5, 10],
                [5, 11],
                [5, 12],
                [5, 13],
                [5, 14],
                [6, 14],
                [7, 14],
                [8, 14],
                [9, 14],
                [10, 14],
                [11, 14],
                [12, 14],
                [13, 14],
                [14, 14],
                [15, 14],
                [16, 14],
                [17, 14],
                [17, 13],
                [17, 12],
                [17, 11],
                [17, 10],
                [17, 9],
                [17, 8],
                [17, 7],
                [18, 7],
                [19, 7],
                [20, 7],
                [21, 7],
                [22, 7],
                [22, 8],
                [23, 8],
                [24, 8]
            ]
        ]
    },
    "rounds": [
        {
            "waves": [
                {
                    "firstCreepSpawnTick": 500,
                    "spawnIntervalTicks": 800,
                    "creeps": [0, 1, 0, 1, 0, 1]
                },
                {
                    "firstCreepSpawnTick": 5000,
                    "spawnIntervalTicks": 600,
                    "creeps": [1, 1, 2, 1, 1, 2]
                }
            ],
            "offeredGems": [0, 1, 2, 3]
        },
        {
            "waves": [
                {
                    "firstCreepSpawnTick": 500,
                    "spawnIntervalTicks": 700,
                    "creeps": [2, 0, 2, 1, 2, 0, 2]
                },
                {
                    "firstCreepSpawnTick": 6000,
                    "spawnIntervalTicks": 500,
                    "creeps": [2, 1, 2, 1, 2, 1, 2]
                }
            ],
            "offeredGems": [0, 1, 2, 3]
        },
        {
            "waves": [
                {
                    "firstCreepSpawnTick": 500,
                    "spawnIntervalTicks": 600,
                    "creeps": [2, 2, 1, 1, 0, 2, 2, 1]
                },
                {
                    "firstCreepSpawnTick": 6000,
                    "spawnIntervalTicks": 400,
                    "creeps": [2, 2, 2, 1, 1, 1, 2, 2]
                }
            ],
            "offeredGems": [0, 1, 2, 3]
        },
        {
            "waves": [
                {
                    "firstCreepSpawnTick": 500,
                    "spawnIntervalTicks": 500,
                    "creeps": [2, 2, 1, 1, 2, 2, 1, 1, 2]
                },
                {
                    "firstCreepSpawnTick": 7000,
                    "spawnIntervalTicks": 300,
                    "creeps": [2, 2, 2, 1, 1, 1, 2, 2, 2]
                }
            ],
            "offeredGems": [0, 1, 2, 3]
        },
        {
            "waves": [
                {
                    "firstCreepSpawnTick": 500,
                    "spawnIntervalTicks": 400,
                    "creeps": [2, 2, 2, 2, 1, 1, 1, 1, 2, 2]
                },
                {
                    "firstCreepSpawnTick": 8000,
                    "spawnIntervalTicks": 250,
                    "creeps": [2, 2, 2, 2, 2, 1, 1, 1, 1, 1]
                }
            ],
            "offeredGems": [0, 1, 2, 3]
        }
    ]
}
